MANIFEST.in
README.rst
setup.py
currency_api/__init__.py
currency_api/converter.py
currency_api.egg-info/PKG-INFO
currency_api.egg-info/SOURCES.txt
currency_api.egg-info/dependency_links.txt
currency_api.egg-info/top_level.txt