Metadata-Version: 1.1
Name: currency-api
Version: 0.0.1
Summary: Gets current dollar values
Home-page: UNKNOWN
Author: Matthew Vasseur
Author-email: mvasseur22@students.hopkins.edu
License: UNKNOWN
Platform: UNKNOWN
Classifier: Programming Language :: Python :: 3
Classifier: License :: OSI Approved :: MIT License
Classifier: Operating System :: OS Independent
